tkitTorchEx/__init__.py
tkitTorchEx/shift_tokens_right.py
tkitTorchEx-0.0.0.116340442.dist-info/LICENSE
tkitTorchEx-0.0.0.116340442.dist-info/METADATA
tkitTorchEx-0.0.0.116340442.dist-info/WHEEL
tkitTorchEx-0.0.0.116340442.dist-info/top_level.txt
tkitTorchEx-0.0.0.116340442.dist-info/RECORD
