Metadata-Version: 2.1
Name: tkitTorchEx
Version: 0.0.0.116340442
Summary: Terry toolkit tkitTorchEx,
Home-page: http://docs.terrychan.org/tkit-lr-pytorch/
Author: Terry Chan
Author-email: napoler2008@gmail.com
License: UNKNOWN
Platform: UNKNOWN
